as_fastapi_toolbox/__init__.py
as_fastapi_toolbox/auth/__init__.py
as_fastapi_toolbox/auth/oidc_token.py
as_fastapi_toolbox/requests/__init__.py
as_fastapi_toolbox/requests/circuit_breaker.py
as_fastapi_toolbox/requests/robust_request.py
as_fastapi_toolbox/validators/__init__.py
as_fastapi_toolbox/validators/csv.py
as_fastapi_toolbox/validators/datetime.py
as_fastapi_toolbox-0.3.6.dist-info/WHEEL
as_fastapi_toolbox-0.3.6.dist-info/METADATA
as_fastapi_toolbox-0.3.6.dist-info/RECORD
